{
  "ones": {
    "#4": 5561,
    "#1": 5531,
    "#5": 5528,
    "#3": 5500,
    "#2": 5486,
    "#0": 3827,
    "#9": 3659,
    "#8": 3605,
    "#7": 3602,
    "#6": 3526
  },
  "tens": {
    "#20": 18369,
    "#10": 18283,
    "#30": 9173
  },
  "sums": {
    "#192": 84,
    "#199": 80,
    "#196": 75,
    "#212": 74,
    "#187": 73,
    "#195": 71,
    "#184": 68,
    "#189": 66,
    "#201": 65,
    "#193": 64,
    "#203": 64,
    "#186": 63,
    "#191": 63,
    "#190": 62,
    "#183": 61,
    "#185": 61,
    "#188": 61,
    "#198": 60,
    "#208": 60,
    "#197": 55,
    "#204": 55,
    "#209": 54,
    "#181": 53,
    "#194": 53,
    "#202": 53,
    "#179": 51,
    "#182": 48,
    "#207": 47,
    "#213": 46,
    "#180": 45,
    "#175": 44,
    "#206": 43,
    "#205": 42,
    "#215": 42,
    "#200": 41,
    "#210": 41,
    "#214": 40,
    "#172": 39,
    "#173": 39,
    "#177": 39,
    "#178": 38,
    "#217": 38,
    "#216": 37,
    "#218": 37,
    "#211": 36,
    "#219": 32,
    "#220": 31,
    "#222": 31,
    "#176": 30,
    "#174": 27,
    "#166": 26,
    "#170": 24,
    "#171": 24,
    "#221": 24,
    "#226": 23,
    "#168": 22,
    "#224": 18,
    "#227": 18,
    "#167": 17,
    "#169": 17,
    "#225": 16,
    "#164": 15,
    "#223": 15,
    "#161": 14,
    "#162": 14,
    "#165": 13,
    "#228": 13,
    "#163": 12,
    "#230": 12,
    "#156": 9,
    "#158": 8,
    "#231": 8,
    "#233": 8,
    "#155": 7,
    "#159": 7,
    "#157": 6,
    "#160": 6,
    "#232": 6,
    "#234": 6,
    "#235": 6,
    "#153": 5,
    "#229": 5,
    "#236": 5,
    "#239": 5,
    "#150": 4,
    "#154": 4,
    "#237": 3,
    "#240": 3,
    "#243": 3,
    "#141": 2,
    "#147": 2,
    "#148": 2,
    "#149": 2,
    "#151": 2,
    "#241": 2,
    "#245": 2,
    "#133": 1,
    "#144": 1,
    "#146": 1,
    "#152": 1,
    "#238": 1,
    "#242": 1,
    "#247": 1,
    "#249": 1
  },
  "mean": {
    "#13": 953,
    "#12": 740,
    "#14": 719,
    "#15": 289,
    "#11": 258,
    "#10": 46,
    "#16": 46,
    "#9": 3,
    "#17": 1
  },
  "pairs": {
    "#7": 942,
    "#8": 782,
    "#6": 639,
    "#9": 354,
    "#5": 211,
    "#10": 83,
    "#4": 30,
    "#11": 11,
    "#3": 3
  },
  "primes": {
    "#5": 937,
    "#6": 885,
    "#4": 537,
    "#7": 437,
    "#3": 141,
    "#8": 93,
    "#2": 15,
    "#9": 8,
    "#1": 2
  },
  "quantity": {
    "#20": 1924,
    "#10": 1903,
    "#11": 1885,
    "#25": 1885,
    "#13": 1862,
    "#24": 1861,
    "#14": 1856,
    "#3": 1849,
    "#4": 1844,
    "#9": 1839,
    "#5": 1838,
    "#12": 1836,
    "#18": 1835,
    "#1": 1830,
    "#2": 1828,
    "#22": 1822,
    "#19": 1820,
    "#21": 1816,
    "#15": 1805,
    "#7": 1801,
    "#17": 1801,
    "#23": 1789,
    "#6": 1781,
    "#8": 1770,
    "#16": 1745
  },
  "sequential": [
    {
      "#11": 137,
      "#1": 136,
      "#10": 135,
      "#20": 133,
      "#9": 132,
      "#22": 132,
      "#23": 131,
      "#21": 128,
      "#13": 127,
      "#3": 126,
      "#4": 126,
      "#25": 125,
      "#18": 123,
      "#16": 122,
      "#24": 122,
      "#14": 120,
      "#19": 119,
      "#5": 117,
      "#7": 117,
      "#8": 116,
      "#15": 111,
      "#12": 109,
      "#2": 106,
      "#6": 105,
      "#17": 100
    },
    {
      "#15": 137,
      "#3": 136,
      "#2": 134,
      "#7": 133,
      "#11": 131,
      "#19": 131,
      "#1": 130,
      "#22": 128,
      "#10": 125,
      "#9": 124,
      "#20": 124,
      "#24": 124,
      "#21": 122,
      "#4": 121,
      "#6": 121,
      "#14": 121,
      "#25": 120,
      "#16": 119,
      "#12": 114,
      "#13": 114,
      "#23": 114,
      "#17": 113,
      "#18": 110,
      "#8": 109,
      "#5": 100
    },
    {
      "#14": 150,
      "#12": 140,
      "#13": 139,
      "#7": 134,
      "#11": 134,
      "#5": 133,
      "#10": 132,
      "#25": 130,
      "#1": 125,
      "#20": 124,
      "#21": 124,
      "#18": 122,
      "#16": 121,
      "#3": 119,
      "#22": 119,
      "#9": 117,
      "#24": 116,
      "#15": 115,
      "#17": 115,
      "#4": 113,
      "#23": 113,
      "#2": 108,
      "#8": 108,
      "#19": 103,
      "#6": 101
    },
    {
      "#5": 145,
      "#19": 141,
      "#7": 135,
      "#20": 133,
      "#24": 131,
      "#12": 130,
      "#13": 129,
      "#4": 128,
      "#17": 127,
      "#25": 127,
      "#2": 119,
      "#6": 119,
      "#22": 119,
      "#3": 117,
      "#11": 117,
      "#21": 117,
      "#1": 116,
      "#8": 116,
      "#10": 115,
      "#14": 115,
      "#18": 115,
      "#16": 114,
      "#15": 113,
      "#9": 109,
      "#23": 108
    },
    {
      "#8": 139,
      "#6": 137,
      "#5": 134,
      "#9": 130,
      "#3": 129,
      "#13": 129,
      "#25": 128,
      "#20": 127,
      "#2": 126,
      "#12": 124,
      "#15": 124,
      "#17": 124,
      "#14": 123,
      "#16": 123,
      "#24": 123,
      "#19": 120,
      "#4": 119,
      "#7": 119,
      "#11": 119,
      "#1": 115,
      "#22": 114,
      "#23": 111,
      "#18": 107,
      "#10": 106,
      "#21": 105
    },
    {
      "#17": 148,
      "#24": 140,
      "#11": 136,
      "#20": 131,
      "#14": 130,
      "#15": 130,
      "#22": 129,
      "#25": 129,
      "#3": 125,
      "#1": 124,
      "#18": 124,
      "#13": 123,
      "#5": 122,
      "#10": 120,
      "#6": 119,
      "#19": 119,
      "#12": 118,
      "#21": 118,
      "#2": 116,
      "#8": 116,
      "#23": 115,
      "#7": 109,
      "#4": 105,
      "#16": 105,
      "#9": 104
    },
    {
      "#3": 144,
      "#12": 139,
      "#9": 134,
      "#13": 132,
      "#14": 132,
      "#1": 130,
      "#19": 130,
      "#18": 129,
      "#22": 129,
      "#16": 127,
      "#20": 127,
      "#2": 123,
      "#5": 123,
      "#25": 122,
      "#11": 119,
      "#17": 119,
      "#6": 117,
      "#21": 115,
      "#23": 115,
      "#15": 114,
      "#24": 111,
      "#8": 110,
      "#7": 107,
      "#4": 105,
      "#10": 102
    },
    {
      "#9": 151,
      "#4": 147,
      "#13": 138,
      "#21": 138,
      "#20": 136,
      "#24": 134,
      "#5": 131,
      "#2": 130,
      "#11": 130,
      "#16": 129,
      "#10": 126,
      "#15": 126,
      "#23": 122,
      "#14": 118,
      "#18": 117,
      "#1": 115,
      "#3": 115,
      "#17": 115,
      "#8": 113,
      "#25": 112,
      "#6": 111,
      "#12": 108,
      "#7": 103,
      "#19": 96,
      "#22": 94
    },
    {
      "#20": 156,
      "#11": 146,
      "#9": 138,
      "#6": 135,
      "#1": 134,
      "#14": 132,
      "#25": 130,
      "#2": 126,
      "#10": 126,
      "#15": 124,
      "#21": 124,
      "#12": 123,
      "#4": 122,
      "#13": 122,
      "#24": 122,
      "#18": 120,
      "#22": 118,
      "#8": 116,
      "#5": 115,
      "#7": 115,
      "#19": 115,
      "#17": 107,
      "#3": 98,
      "#16": 96,
      "#23": 95
    },
    {
      "#2": 139,
      "#24": 138,
      "#4": 137,
      "#3": 136,
      "#20": 135,
      "#7": 130,
      "#10": 130,
      "#19": 130,
      "#9": 126,
      "#21": 126,
      "#1": 125,
      "#25": 122,
      "#13": 121,
      "#16": 121,
      "#23": 120,
      "#11": 118,
      "#17": 118,
      "#18": 117,
      "#12": 116,
      "#6": 113,
      "#8": 112,
      "#5": 110,
      "#14": 106,
      "#22": 106,
      "#15": 103
    },
    {
      "#6": 141,
      "#20": 140,
      "#19": 138,
      "#15": 134,
      "#17": 133,
      "#24": 132,
      "#22": 131,
      "#25": 130,
      "#14": 128,
      "#13": 125,
      "#10": 124,
      "#12": 124,
      "#18": 120,
      "#3": 119,
      "#7": 119,
      "#23": 119,
      "#11": 118,
      "#4": 116,
      "#2": 115,
      "#16": 113,
      "#8": 112,
      "#1": 111,
      "#5": 107,
      "#9": 106,
      "#21": 100
    },
    {
      "#12": 139,
      "#4": 134,
      "#8": 133,
      "#24": 131,
      "#21": 129,
      "#25": 129,
      "#5": 127,
      "#1": 125,
      "#16": 124,
      "#23": 124,
      "#9": 123,
      "#10": 123,
      "#11": 122,
      "#17": 122,
      "#3": 121,
      "#22": 121,
      "#18": 120,
      "#19": 120,
      "#2": 118,
      "#20": 118,
      "#15": 117,
      "#7": 114,
      "#14": 113,
      "#6": 109,
      "#13": 99
    },
    {
      "#18": 146,
      "#25": 144,
      "#4": 142,
      "#14": 140,
      "#10": 138,
      "#5": 133,
      "#8": 128,
      "#7": 126,
      "#23": 126,
      "#3": 122,
      "#13": 122,
      "#9": 121,
      "#17": 119,
      "#22": 118,
      "#1": 117,
      "#11": 117,
      "#19": 116,
      "#6": 112,
      "#15": 111,
      "#21": 111,
      "#24": 111,
      "#2": 110,
      "#16": 110,
      "#20": 110,
      "#12": 105
    },
    {
      "#10": 156,
      "#15": 139,
      "#18": 136,
      "#17": 134,
      "#22": 133,
      "#2": 131,
      "#5": 129,
      "#23": 126,
      "#21": 125,
      "#6": 124,
      "#12": 123,
      "#13": 123,
      "#7": 122,
      "#8": 121,
      "#16": 118,
      "#1": 117,
      "#14": 116,
      "#24": 116,
      "#3": 115,
      "#11": 115,
      "#19": 112,
      "#4": 110,
      "#9": 106,
      "#20": 105,
      "#25": 103
    },
    {
      "#23": 150,
      "#10": 145,
      "#21": 134,
      "#25": 134,
      "#22": 131,
      "#19": 130,
      "#18": 129,
      "#2": 127,
      "#3": 127,
      "#11": 126,
      "#20": 125,
      "#12": 124,
      "#8": 121,
      "#4": 119,
      "#13": 119,
      "#7": 118,
      "#9": 118,
      "#6": 117,
      "#5": 112,
      "#14": 112,
      "#1": 110,
      "#24": 110,
      "#15": 107,
      "#17": 107,
      "#16": 103
    }
  ]
}